excel_provider/__init__.py
excel_provider/__main__.py
excel_provider/io/excel.py
excel_provider/rest/api.py
excel_provider/rest/handler.py
excel_provider-0.1.4.dist-info/LICENSE
excel_provider-0.1.4.dist-info/METADATA
excel_provider-0.1.4.dist-info/WHEEL
excel_provider-0.1.4.dist-info/RECORD
