Metadata-Version: 2.1
Name: excel-provider
Version: 0.1.4
Summary: 
Home-page: https://github.com/cybernop/excel-provider
License: MIT
Author: Alexander Essenwanger
Author-email: cibernop@mable-anex.de
Requires-Python: >=3.11,<4.0
Classifier: License :: OSI Approved :: MIT License
Classifier: Programming Language :: Python :: 3
Classifier: Programming Language :: Python :: 3.11
Classifier: Programming Language :: Python :: 3.12
Requires-Dist: flask (>=3.0.2,<4.0.0)
Requires-Dist: flask-swagger (>=0.2.14,<0.3.0)
Requires-Dist: openpyxl (>=3.1.2,<4.0.0)
Requires-Dist: pandas (>=2.2,<3.0)
Requires-Dist: pyyaml (>=6.0.1,<7.0.0)
Project-URL: Repository, https://github.com/cybernop/excel-provider
